yang/__init__.py
yang/test.py
pungyoung-1.0.0.dist-info/METADATA
pungyoung-1.0.0.dist-info/WHEEL
pungyoung-1.0.0.dist-info/top_level.txt
pungyoung-1.0.0.dist-info/RECORD
